{
  "multipart": [
    {
      "apply": {
        "model": "depthsupdate:polished_deepslate_wall_post"
      },
      "when": {
        "up": "true"
      }
    },
    {
      "apply": {
        "model": "depthsupdate:polished_deepslate_wall_side",
        "uvlock": true
      },
      "when": {
        "north": "true"
      }
    },
    {
      "apply": {
        "y": 90,
        "uvlock": true,
        "model": "depthsupdate:polished_deepslate_wall_side"
      },
      "when": {
        "east": "true"
      }
    },
    {
      "apply": {
        "y": 180,
        "uvlock": true,
        "model": "depthsupdate:polished_deepslate_wall_side"
      },
      "when": {
        "south": "true"
      }
    },
    {
      "apply": {
        "y": 270,
        "uvlock": true,
        "model": "depthsupdate:polished_deepslate_wall_side"
      },
      "when": {
        "west": "true"
      }
    }
  ],
  "variants": {
    "variant=cobblestone": {
      "model": "depthsupdate:polished_deepslate_wall_inventory"
    }
  }
}
